kronjob.py
kronjob-0.0.4.dist-info/DESCRIPTION.rst
kronjob-0.0.4.dist-info/METADATA
kronjob-0.0.4.dist-info/RECORD
kronjob-0.0.4.dist-info/WHEEL
kronjob-0.0.4.dist-info/entry_points.txt
kronjob-0.0.4.dist-info/metadata.json
kronjob-0.0.4.dist-info/top_level.txt
