Metadata-Version: 2.0
Name: kronjob
Version: 0.0.4
Summary: Generate Kubernetes Job/CronJob specs without the boilerplate.
Home-page: https://github.com/better/kronjob
Author: Better Mortgage
Author-email: accounts@better.com
License: UNKNOWN
Keywords: kubernetes job cronjob schedule template
Platform: UNKNOWN
Requires-Dist: kubernetes (==4.0.0)
Requires-Dist: marshmallow (==3.0.0b7)
Requires-Dist: python-crontab (==2.2.8)
Requires-Dist: PyYAML (==3.12)
